[
 {
  "VideoID": "1",
  "CustomerID": "2",
  "IssueDate": "03/21/2022"
 },
 {
  "VideoID": "4",
  "CustomerID": "4",
  "IssueDate": "03/21/2022"
 },
 {
  "VideoID": "5",
  "CustomerID": "5",
  "IssueDate": "03/21/2022"
 },
 {
  "VideoID": "8",
  "CustomerID": "9",
  "IssueDate": "03/21/2022"
 },
 {
  "VideoID": "3",
  "CustomerID": "3",
  "IssueDate": "03/21/2022"
 },
 {
  "VideoID": "11",
  "CustomerID": "12",
  "IssueDate": "03/21/2022"
 },
 {
  "VideoID": "f",
  "CustomerID": "g",
  "IssueDate": "03/21/2022"
 },
 {
  "VideoID": "66",
  "CustomerID": "77",
  "IssueDate": "03/21/2022"
 },
 {
  "VideoID": "88",
  "CustomerID": "9",
  "IssueDate": "03/22/2022"
 }
]